README.md
setup.py
appseed_shell/__init__.py
appseed_shell/appseed_shell.py
appseed_shell/submodule.py
appseed_shell.egg-info/PKG-INFO
appseed_shell.egg-info/SOURCES.txt
appseed_shell.egg-info/dependency_links.txt
appseed_shell.egg-info/not-zip-safe
appseed_shell.egg-info/requires.txt
appseed_shell.egg-info/top_level.txt