Metadata-Version: 2.1
Name: appseed-shell
Version: 0.0.4
Summary: Implements the Python interface to all services exposed by AppSeed
Home-page: https://github.com/app-generator/appseed-shell-py
Author: AppSeed.us
Author-email: support@appseed.us
License: MIT License
Platform: UNKNOWN
Classifier: Intended Audience :: Developers
Classifier: Intended Audience :: System Administrators
Classifier: License :: OSI Approved :: MIT License
Classifier: Operating System :: OS Independent
Classifier: Programming Language :: Python
Classifier: Programming Language :: Python :: 2.6
Classifier: Programming Language :: Python :: 2.7
Classifier: Programming Language :: Python :: 3.2
Classifier: Programming Language :: Python :: 3.3
Classifier: Programming Language :: Python :: 3.4
Classifier: Programming Language :: Python :: 3.5
Classifier: Programming Language :: Python :: 3.6
Classifier: Environment :: Web Environment
Classifier: Topic :: Software Development
Classifier: Topic :: Software Development :: User Interfaces
